leda_upc.cpython-313-x86_64-linux-gnu.so
leda_upc-1.0.dist-info/METADATA
leda_upc-1.0.dist-info/WHEEL
leda_upc-1.0.dist-info/top_level.txt
leda_upc-1.0.dist-info/RECORD
