Metadata-Version: 2.4
Name: leda-upc
Version: 1.0
Summary: Encrypted ODOO module
Author-email: RoyZ <2820003660@qq.com>
License: GPL-3.0-or-later
Platform: any
Requires-Python: >=3.7
Requires-Dist: pybind11>=2.6.0
Dynamic: platform
Dynamic: requires-python
